lh/__init__.py
lh-0.0.5.dist-info/licenses/LICENSE
lh-0.0.5.dist-info/METADATA
lh-0.0.5.dist-info/WHEEL
lh-0.0.5.dist-info/top_level.txt
lh-0.0.5.dist-info/RECORD
