Metadata-Version: 2.4
Name: lh
Version: 0.0.5
Summary: logging functions
Home-page: https://github.com/t-c-w/lh
Author: Thor Whalen
License: apache-2.0
Platform: any
License-File: LICENSE
Dynamic: license-file
